protobuf2pydantic/__init__.py
protobuf2pydantic/biz.py
protobuf2pydantic/main.py
tests/__init__.py
tests/celery_task_pb2.py
tests/test___init__.py
tests/test_biz.py
tests/test_main.py
tests/test_map_pb2.py
tests/test_pb2.py
protobuf2pydantic-2024.4.18.dist-info/LICENSE
protobuf2pydantic-2024.4.18.dist-info/METADATA
protobuf2pydantic-2024.4.18.dist-info/WHEEL
protobuf2pydantic-2024.4.18.dist-info/entry_points.txt
protobuf2pydantic-2024.4.18.dist-info/top_level.txt
protobuf2pydantic-2024.4.18.dist-info/RECORD
