Metadata-Version: 2.1
Name: protobuf2pydantic
Version: 2024.4.18
Summary: Generate a file which include pydantic models by protobuf.pb2 file
Home-page: https://github.com/Ed-XCF/protobuf2pydantic
Author: Ed__xu__Ed
Author-email: m.tofu@qq.com
Classifier: Programming Language :: Python :: 3
Classifier: License :: OSI Approved :: MIT License
Classifier: Operating System :: OS Independent
Requires-Python: >=3.6
License-File: LICENSE
Requires-Dist: grpcio >=1.32.0
Requires-Dist: grpcio-tools >=1.32.0
Requires-Dist: typer >=0.3.2
Requires-Dist: pydantic >=1.7.3
